async_faceit_api/__init__.py
async_faceit_api/api.py
async_faceit_api/dataclasses.py
async_faceit_api/enums.py
async_faceit_api-0.1.7.dist-info/METADATA
async_faceit_api-0.1.7.dist-info/WHEEL
async_faceit_api-0.1.7.dist-info/licenses/LICENSE
async_faceit_api-0.1.7.dist-info/RECORD
