Metadata-Version: 2.3
Name: async_faceit_api
Version: 0.1.7
Summary: Async wrapper for the faceit API
Project-URL: Homepage, https://github.com/StuartTheYellowOne/async_faceit_api
Project-URL: Bug Tracker, https://github.com/StuartTheYellowOne/async_faceit_api/issues
Author-email: Stuart <stuart.the.yellow.one@gmail.com>
License-File: LICENSE
Classifier: License :: OSI Approved :: MIT License
Classifier: Operating System :: OS Independent
Classifier: Programming Language :: Python :: 3
Requires-Python: >=3.8
Requires-Dist: aiohttp<3.9.5
